Metadata-Version: 2.1
Name: bisneto-mathlib
Version: 0.0.2
Summary: Math Library
Home-page: https://github.com/hbisneto/Mathematics
Author: Heitor Bisneto
Author-email: heitor.bardemaker@live.com
License: MIT License
Keywords: mathlib
Platform: UNKNOWN
